trololio.py
Trololio-1.0.dist-info/DESCRIPTION.rst
Trololio-1.0.dist-info/METADATA
Trololio-1.0.dist-info/metadata.json
Trololio-1.0.dist-info/RECORD
Trololio-1.0.dist-info/top_level.txt
Trololio-1.0.dist-info/WHEEL
